dataprep/.DS_Store
dataprep/__init__.py
dataprep/assets/ellipse.npz
dataprep/assets/english_stopwords.py
dataprep/clean/.DS_Store
dataprep/clean/__init__.py
dataprep/clean/address_utils.py
dataprep/clean/clean_ad_nrt.py
dataprep/clean/clean_address.py
dataprep/clean/clean_al_nipt.py
dataprep/clean/clean_ar_cbu.py
dataprep/clean/clean_ar_cuit.py
dataprep/clean/clean_ar_dni.py
dataprep/clean/clean_at_uid.py
dataprep/clean/clean_at_vnr.py
dataprep/clean/clean_au_abn.py
dataprep/clean/clean_au_acn.py
dataprep/clean/clean_au_tfn.py
dataprep/clean/clean_be_iban.py
dataprep/clean/clean_be_vat.py
dataprep/clean/clean_bg_egn.py
dataprep/clean/clean_bg_pnf.py
dataprep/clean/clean_bg_vat.py
dataprep/clean/clean_bic.py
dataprep/clean/clean_bitcoin.py
dataprep/clean/clean_br_cnpj.py
dataprep/clean/clean_br_cpf.py
dataprep/clean/clean_by_unp.py
dataprep/clean/clean_ca_bn.py
dataprep/clean/clean_ca_sin.py
dataprep/clean/clean_casrn.py
dataprep/clean/clean_ch_esr.py
dataprep/clean/clean_ch_ssn.py
dataprep/clean/clean_ch_uid.py
dataprep/clean/clean_ch_vat.py
dataprep/clean/clean_cl_rut.py
dataprep/clean/clean_cn_ric.py
dataprep/clean/clean_cn_uscc.py
dataprep/clean/clean_co_nit.py
dataprep/clean/clean_country.py
dataprep/clean/clean_cr_cpf.py
dataprep/clean/clean_cr_cpj.py
dataprep/clean/clean_cr_cr.py
dataprep/clean/clean_cu_ni.py
dataprep/clean/clean_currency.py
dataprep/clean/clean_cusip.py
dataprep/clean/clean_cy_vat.py
dataprep/clean/clean_cz_dic.py
dataprep/clean/clean_cz_rc.py
dataprep/clean/clean_date.py
dataprep/clean/clean_date_utils.py
dataprep/clean/clean_de_handelsregisternummer.py
dataprep/clean/clean_de_idnr.py
dataprep/clean/clean_de_stnr.py
dataprep/clean/clean_de_vat.py
dataprep/clean/clean_de_wkn.py
dataprep/clean/clean_df.py
dataprep/clean/clean_df_gui.py
dataprep/clean/clean_dk_cpr.py
dataprep/clean/clean_dk_cvr.py
dataprep/clean/clean_do_cedula.py
dataprep/clean/clean_do_ncf.py
dataprep/clean/clean_do_rnc.py
dataprep/clean/clean_duplication.py
dataprep-0.4.4.dist-info/LICENSE
dataprep-0.4.4.dist-info/WHEEL
dataprep-0.4.4.dist-info/METADATA
dataprep-0.4.4.dist-info/RECORD
