Metadata-Version: 2.1
Name: dataprep
Version: 0.4.4
Summary: Dataprep: Data Preparation in Python
Home-page: https://github.com/sfu-db/dataprep
License: MIT
Keywords: dataprep,eda,connector,data science,exploratory data analysis,data exploration
Author: SFU Database System Lab
Author-email: dsl.cs.sfu@gmail.com
Maintainer: Weiyuan Wu
Maintainer-email: youngw@sfu.com
Requires-Python: >=3.8,<3.11
Classifier: Development Status :: 4 - Beta
Classifier: Environment :: Console
Classifier: Framework :: IPython
Classifier: Intended Audience :: Developers
Classifier: Intended Audience :: Financial and Insurance Industry
Classifier: Intended Audience :: Healthcare Industry
Classifier: Intended Audience :: Science/Research
Classifier: License :: OSI Approved :: MIT License
Classifier: Operating System :: OS Independent
Classifier: Programming Language :: Python :: 3
Classifier: Programming Language :: Python :: 3.10
Classifier: Programming Language :: Python :: 3.8
Classifier: Programming Language :: Python :: 3.9
Classifier: Topic :: Scientific/Engineering
Classifier: Topic :: Software Development :: Build Tools
Requires-Dist: aiohttp (>=3.6,<4.0)
Requires-Dist: bokeh (>=2,<3)
Requires-Dist: dask[dataframe,delayed,array] (>=2022.3.0)
Requires-Dist: flask (>=2,<3)
Requires-Dist: flask_cors (>=3.0.10,<4.0.0)
Requires-Dist: ipywidgets (>=7.5,<8.0)
Requires-Dist: jinja2 (>=3.0,<3.1)
Requires-Dist: jsonpath-ng (>=1.5,<2.0)
Requires-Dist: metaphone (>=0.6,<0.7)
Requires-Dist: nltk (>=3.6.7,<4.0.0)
Requires-Dist: numpy (>=1.21,<2.0)
Requires-Dist: pandas (>=1.1,<2.0)
Requires-Dist: pydantic (>=1.6,<2.0)
Requires-Dist: python-crfsuite (==0.9.8)
Requires-Dist: python-stdnum (>=1.16,<2.0)
Requires-Dist: rapidfuzz (>=2.1.2,<3.0.0)
Requires-Dist: regex (>=2021.8.3,<2022.0.0)
Requires-Dist: scipy (>=1.8,<2.0)
Requires-Dist: sqlalchemy (>=1.4.32,<2.0.0)
Requires-Dist: tqdm (>=4.48,<5.0)
Requires-Dist: varname (>=0.8.1,<0.9.0)
Requires-Dist: wordcloud (>=1.8,<2.0)
Project-URL: Repository, https://github.com/sfu-db/dataprep
